dutils/__init__.py
dutils/bbox.py
dutils/constants.py
dutils/dutils.py
dutils/metrics.py
dutils/points.py
dutils/transforms.py
dutils/voxelgrid.py
dutils_python-0.6.7.6.dist-info/LICENSE
dutils_python-0.6.7.6.dist-info/METADATA
dutils_python-0.6.7.6.dist-info/WHEEL
dutils_python-0.6.7.6.dist-info/top_level.txt
dutils_python-0.6.7.6.dist-info/RECORD
